README.rst
setup.cfg
setup.py
django_treemenus2.egg-info/PKG-INFO
django_treemenus2.egg-info/SOURCES.txt
django_treemenus2.egg-info/dependency_links.txt
django_treemenus2.egg-info/not-zip-safe
django_treemenus2.egg-info/requires.txt
django_treemenus2.egg-info/top_level.txt
treemenus/__init__.py
treemenus/admin.py
treemenus/config.py
treemenus/models.py
treemenus/utils.py
treemenus/migrations/0001_initial.py
treemenus/migrations/__init__.py
treemenus/static/img/treemenus/arrow-down.gif
treemenus/static/img/treemenus/arrow-up.gif
treemenus/static/img/treemenus/icon_addlink.gif
treemenus/templates/admin/treemenus/menu/change_form.html
treemenus/templates/admin/treemenus/menuitem/change_form.html
treemenus/templates/admin/treemenus/menuitem/delete_confirmation.html
treemenus/templates/admin/treemenus/menuitem/object_history.html
treemenus/templatetags/__init__.py
treemenus/templatetags/tree_menu_tags.py
treemenus/tests/__init__.py
treemenus/tests/settings.py
treemenus/tests/test_treemenus.py
treemenus/tests/urls.py
treemenus/tests/fake_menu_extension/__init__.py
treemenus/tests/fake_menu_extension/admin.py
treemenus/tests/fake_menu_extension/models.py